{"autotest_index.md":"f96cc014","autotest_phpunit.md":"0cfdc04b","autotest_selenium.md":"fa5e63fb","compose.md":"3d85b9c8","docker_command.md":"fa29b75e","docker_index.md":"ff061661","docker_question.md":"cbc4e8fb","docker_setup.md":"d748e184","index.md":"de92a438","notes_index.md":"86366b52","notes_java.md":"c92c66c5","notes_maven.md":"7684e141","rabbitmq_code.md":"a277b0c7","rabbitmq_command.md":"0eb2ecd7","rabbitmq_config.md":"38558ec0","rabbitmq_deploy.md":"449930ac","rabbitmq_index.md":"2872b51a","rabbitmq_question.md":"a072a7a9","sites_index.md":"2cbdd944","solr_code.md":"0fac86cc","solr_deploy.md":"69a24450","solr_index.md":"46a9eb84","standard_component.md":"233fd99a","standard_db.md":"01277975","standard_html.md":"4bff5e20","standard_toolbox.md":"f4d1dca8","standard_ui.md":"a5e5bda9","tools_index.md":"91021395","view_command.md":"92fece7a","view_index.md":"49e89dac","view_live.md":"94c2afac","view_local.md":"79179b26","view_question.md":"90fd3027","wso2_consumer.md":"69827720","wso2_deploy.md":"bc385d6d","wso2_docs.md":"04299c96","wso2_ei.md":"85fac8d2","wso2_index.md":"456a0064","wso2_producer.md":"ba0737be","wso2_setup.md":"8560f752","wso2_test.md":"315e1da9"}
